[
    {
        "name":"Customer Support", 
        "adress" :"Toshkent shahri , Chilonzor tumani , Bunyodkor ko'chasi",
        "telephone":"+998939542111",
        "email_adress" : " Example@gmail.com"
    },
    {
        "name":"Customer Support", 
        "adress" :"Toshkent shahri , Chilonzor tumani , Bunyodkor ko'chasi",
        "telephone":"+998939542111",
        "email_adress" : " Example@gmail.com"
    },
    {
        "name":"Customer Support", 
        "adress" :"Toshkent shahri , Chilonzor tumani , Bunyodkor ko'chasi",
        "telephone":"+998939542111",
        "email_adress" : " Example@gmail.com"
    }
]